uvx_excel_read_dbmod/__init__.py
uvx_excel_read_dbmod/server.py
uvx_excel_read_dbmod/base_mod/__init__.py
uvx_excel_read_dbmod/base_mod/excel_manager.py
uvx_excel_read_dbmod/base_mod/pandas.py
uvx_excel_read_dbmod/base_mod/polars.py
uvx_excel_read_dbmod/tools/__init__.py
uvx_excel_read_dbmod/tools/advanced_group_by/__init__.py
uvx_excel_read_dbmod/tools/advanced_group_by/tool.py
uvx_excel_read_dbmod/tools/get_sheet_list/__init__.py
uvx_excel_read_dbmod/tools/get_sheet_list/tool.py
uvx_excel_read_dbmod/tools/group_by_sheet_title_get_count_and_values/__init__.py
uvx_excel_read_dbmod/tools/group_by_sheet_title_get_count_and_values/tool.py
uvx_excel_read_dbmod/tools/query_by_sql/__init__.py
uvx_excel_read_dbmod/tools/query_by_sql/tool.py
uvx_excel_read_dbmod/tools/search_row_in_sheet_by_keyword/__init__.py
uvx_excel_read_dbmod/tools/search_row_in_sheet_by_keyword/tool.py
uvx_excel_read_dbmod/tools/select_count_sheet_rows/__init__.py
uvx_excel_read_dbmod/tools/select_count_sheet_rows/tool.py
uvx_excel_read_dbmod/tools/select_sheet_rows_by_id/__init__.py
uvx_excel_read_dbmod/tools/select_sheet_rows_by_id/tool.py
uvx_excel_read_dbmod/tools/select_sheet_rows_by_title_where/__init__.py
uvx_excel_read_dbmod/tools/select_sheet_rows_by_title_where/tool.py
uvx_excel_read_dbmod-0.2.1.dist-info/METADATA
uvx_excel_read_dbmod-0.2.1.dist-info/WHEEL
uvx_excel_read_dbmod-0.2.1.dist-info/entry_points.txt
uvx_excel_read_dbmod-0.2.1.dist-info/RECORD
