Metadata-Version: 2.4
Name: uvx-excel-read-dbmod
Version: 0.2.1
Summary: 用数据库的方式提供读取、分析 Excel 文件的 MCP 服务
Requires-Python: >=3.12
Requires-Dist: fastexcel>=0.7.0
Requires-Dist: fastmcp>=2.14.2
Requires-Dist: openpyxl>=3.1.0
Requires-Dist: pandas>=2.0.0
Requires-Dist: polars>=0.20.0
Requires-Dist: xlrd>=2.0.0
